kafka_python_with_confluent_kafka/kafka_admin.py
kafka_python_with_confluent_kafka/kafka_consumer.py
kafka_python_with_confluent_kafka/kafka_producer.py
kafka_python_with_confluent_kafka-0.2.dist-info/LICENSE
kafka_python_with_confluent_kafka-0.2.dist-info/METADATA
kafka_python_with_confluent_kafka-0.2.dist-info/WHEEL
kafka_python_with_confluent_kafka-0.2.dist-info/top_level.txt
kafka_python_with_confluent_kafka-0.2.dist-info/RECORD
