Metadata-Version: 2.1
Name: kafka-python-with-confluent-kafka
Version: 0.2
Summary: This python project use to consume/produce/manager the Kafka
Home-page: https://gitlab.com/py2kpy2k/kafka-python-with-confluent-kafka.git
Author: py2k
Author-email: py2kpy2k@gmail.com
License: UNKNOWN
Download-URL: https://gitlab.com/py2kpy2k/kafka-python-with-confluent-kafka/tags/v0.2
Keywords: kafka,kafka-admin,kafka-consumer,kafka-producer
Platform: UNKNOWN
Requires-Dist: kafka-python (>=1.4)
Requires-Dist: confluent-kafka
